[
  {
    "id": "RiT-WxJgvOW",
    "url": "https://www.instagram.com/reel/RiT-WxJgvOW/",
    "ownerUsername": "beauty_md3",
    "caption": "Rejuvenate your skin with facial treatment for younger looking skin! #cosmetology #beauty #clinic #facial",
    "viewCount": 232187,
    "likeCount": 20097,
    "commentCount": 1672,
    "timestamp": "2025-05-05T00:31:55.603Z",
    "hashtags": [
      "#cosmetology",
      "#beauty",
      "#clinic",
      "#facial"
    ],
    "type": "reel"
  },
  {
    "id": "E3-HTr6Bt-8",
    "url": "https://www.instagram.com/reel/E3-HTr6Bt-8/",
    "ownerUsername": "face_spa",
    "caption": "Experience the power of medical procedure for clear complexion! #cosmetology #skincare #aestheticmedicine #transformation #beauty",
    "viewCount": 480078,
    "likeCount": 10508,
    "commentCount": 925,
    "timestamp": "2025-05-20T04:03:12.608Z",
    "hashtags": [
      "#cosmetology",
      "#skincare",
      "#aestheticmedicine",
      "#transformation",
      "#beauty"
    ],
    "type": "reel"
  },
  {
    "id": "HnY05m8CV_c",
    "url": "https://www.instagram.com/reel/HnY05m8CV_c/",
    "ownerUsername": "clinic_spa5",
    "caption": "Experience the power of beauty treatment for younger looking skin! #cosmetology #facial #beauty #results",
    "viewCount": 138472,
    "likeCount": 6859,
    "commentCount": 662,
    "timestamp": "2025-05-09T18:31:03.121Z",
    "hashtags": [
      "#cosmetology",
      "#facial",
      "#beauty",
      "#results"
    ],
    "type": "reel"
  },
  {
    "id": "e3LdxTPSYyD",
    "url": "https://www.instagram.com/reel/e3LdxTPSYyD/",
    "ownerUsername": "aesthetic_spa",
    "caption": "Check out our latest aesthetic procedure for radiant skin! #cosmetology #results #facial #professional #transformation",
    "viewCount": 170965,
    "likeCount": 11090,
    "commentCount": 1050,
    "timestamp": "2025-05-04T20:29:56.057Z",
    "hashtags": [
      "#cosmetology",
      "#results",
      "#facial",
      "#professional",
      "#transformation"
    ],
    "type": "reel"
  },
  {
    "id": "N6i3kzc8piG",
    "url": "https://www.instagram.com/reel/N6i3kzc8piG/",
    "ownerUsername": "aesthetic_official5",
    "caption": "Transform your skin with skin rejuvenation for younger looking skin! #cosmetology #transformation #professional #results",
    "viewCount": 322910,
    "likeCount": 22772,
    "commentCount": 583,
    "timestamp": "2025-05-13T23:55:00.430Z",
    "hashtags": [
      "#cosmetology",
      "#transformation",
      "#professional",
      "#results"
    ],
    "type": "reel"
  },
  {
    "id": "imnnS8r7qK8",
    "url": "https://www.instagram.com/reel/imnnS8r7qK8/",
    "ownerUsername": "cosmo_beauty",
    "caption": "Experience the power of clinic procedure for radiant skin! #cosmetology #skincare #transformation #facial",
    "viewCount": 348672,
    "likeCount": 8187,
    "commentCount": 722,
    "timestamp": "2025-05-16T17:12:22.862Z",
    "hashtags": [
      "#cosmetology",
      "#skincare",
      "#transformation",
      "#facial"
    ],
    "type": "reel"
  },
  {
    "id": "jr9xeg2NI5m",
    "url": "https://www.instagram.com/reel/jr9xeg2NI5m/",
    "ownerUsername": "face_center",
    "caption": "Amazing results with hydrafacial treatment for younger looking skin! #cosmetology #results #beauty #clinic",
    "viewCount": 194361,
    "likeCount": 11120,
    "commentCount": 296,
    "timestamp": "2025-04-25T23:52:57.060Z",
    "hashtags": [
      "#cosmetology",
      "#results",
      "#beauty",
      "#clinic"
    ],
    "type": "reel"
  },
  {
    "id": "cwld2i4GuyR",
    "url": "https://www.instagram.com/reel/cwld2i4GuyR/",
    "ownerUsername": "skin_expert0",
    "caption": "Check out our latest skin rejuvenation for glowing skin! #cosmetology #transformation #aestheticmedicine #beauty #facial",
    "viewCount": 98731,
    "likeCount": 5232,
    "commentCount": 259,
    "timestamp": "2025-05-01T02:35:56.654Z",
    "hashtags": [
      "#cosmetology",
      "#transformation",
      "#aestheticmedicine",
      "#beauty",
      "#facial"
    ],
    "type": "reel"
  },
  {
    "id": "bxhygZHArr6",
    "url": "https://www.instagram.com/reel/bxhygZHArr6/",
    "ownerUsername": "face_official4",
    "caption": "Amazing results with beauty treatment for radiant skin! #cosmetology #professional #beauty #aestheticmedicine",
    "viewCount": 170078,
    "likeCount": 12832,
    "commentCount": 1251,
    "timestamp": "2025-05-07T14:51:33.598Z",
    "hashtags": [
      "#cosmetology",
      "#professional",
      "#beauty",
      "#aestheticmedicine"
    ],
    "type": "reel"
  },
  {
    "id": "PysXaVVvD8T",
    "url": "https://www.instagram.com/reel/PysXaVVvD8T/",
    "ownerUsername": "derma_beauty2",
    "caption": "Professional results with spa treatment for radiant skin! #cosmetology #treatment #transformation #skincare",
    "viewCount": 420706,
    "likeCount": 17337,
    "commentCount": 1061,
    "timestamp": "2025-05-09T05:15:37.710Z",
    "hashtags": [
      "#cosmetology",
      "#treatment",
      "#transformation",
      "#skincare"
    ],
    "type": "reel"
  }
]